interactions/ext/dbl/__init__.py
interactions/ext/dbl/client.py
interactions/ext/dbl/exceptions.py
interactions_dbl-1.0.0.dist-info/LICENSE
interactions_dbl-1.0.0.dist-info/METADATA
interactions_dbl-1.0.0.dist-info/WHEEL
interactions_dbl-1.0.0.dist-info/top_level.txt
interactions_dbl-1.0.0.dist-info/RECORD
