Metadata-Version: 2.1
Name: interactions-dbl
Version: 1.0.0
Summary: DBL (Discord Bot Lists) extension library for discord-py-interactions
Home-page: https://github.com/rahul-nanwani/interactions-dbl
Author: Rahul Nanwani
Author-email: rahulnanwani@icloud.com
License: MIT
Project-URL: Documentation, https://github.com/rahul-nanwani/interactions-dbl/wiki
Project-URL: Source, https://github.com/rahul-nanwani/interactions-dbl
Project-URL: Tracker, https://github.com/rahul-nanwani/interactions-dbl.git
Classifier: Programming Language :: Python :: 3
Classifier: Development Status :: 5 - Production/Stable
Classifier: License :: OSI Approved :: MIT License
Classifier: Operating System :: OS Independent
Classifier: Intended Audience :: Developers
License-File: LICENSE
Requires-Dist: aiohttp (~=3.8.0)
Requires-Dist: discord-py-interactions (~=4.3.0)
